up2oss.py
up2oss-0.1.5.dist-info/LICENSE
up2oss-0.1.5.dist-info/METADATA
up2oss-0.1.5.dist-info/WHEEL
up2oss-0.1.5.dist-info/top_level.txt
up2oss-0.1.5.dist-info/RECORD
