Metadata-Version: 2.1
Name: up2oss
Version: 0.1.5
Summary: Save uploaded pictures in Aliyun OSS.
Home-page: https://github.com/staugur/picbed-up2oss
Author: staugur
Author-email: staugur@saintic.com
License: BSD 3-Clause
Platform: UNKNOWN
Requires-Dist: oss2 (>2.0.0)
